<?xml version="1.0" encoding="ISO-8859-1"?>
<!--
     Attention: Generated code! Do not modify by hand!
     Generated by: hibernate3/hibernate.hbm.xml.vsl in andromda-hibernate-cartridge.
  -->
<!DOCTYPE hibernate-mapping PUBLIC "-//Hibernate/Hibernate Mapping DTD 3.0//EN"
          "http://www.hibernate.org/dtd/hibernate-mapping-3.0.dtd">

<hibernate-mapping default-cascade="none">
    <class name="mwk.pptp.androdomain.MouseCrosstabImpl"
        table="MOUSE_CROSSTAB" dynamic-insert="false" dynamic-update="false">
        <id name="id" type="java.lang.Long" unsaved-value="null">
            <column name="ID" sql-type="BIGINT"/>
            <generator class="native">
                <!-- id-generator merge-point -->
            </generator>
        </id>
        <property name="mouse1">
            <column name="MOUSE1" not-null="false" unique="true" sql-type="DOUBLE PRECISION"/>
            <type name="java.lang.Double"/>
        </property>
        <property name="mouse2">
            <column name="MOUSE2" not-null="false" unique="true" sql-type="DOUBLE PRECISION"/>
            <type name="java.lang.Double"/>
        </property>
        <property name="mouse3">
            <column name="MOUSE3" not-null="false" unique="true" sql-type="DOUBLE PRECISION"/>
            <type name="java.lang.Double"/>
        </property>
        <property name="mouse4">
            <column name="MOUSE4" not-null="false" unique="true" sql-type="DOUBLE PRECISION"/>
            <type name="java.lang.Double"/>
        </property>
        <property name="mouse5">
            <column name="MOUSE5" not-null="false" unique="true" sql-type="DOUBLE PRECISION"/>
            <type name="java.lang.Double"/>
        </property>
        <property name="mouse6">
            <column name="MOUSE6" not-null="false" unique="true" sql-type="DOUBLE PRECISION"/>
            <type name="java.lang.Double"/>
        </property>
        <property name="mouse7">
            <column name="MOUSE7" not-null="false" unique="true" sql-type="DOUBLE PRECISION"/>
            <type name="java.lang.Double"/>
        </property>
        <property name="mouse8">
            <column name="MOUSE8" not-null="false" unique="true" sql-type="DOUBLE PRECISION"/>
            <type name="java.lang.Double"/>
        </property>
        <property name="mouse9">
            <column name="MOUSE9" not-null="false" unique="true" sql-type="DOUBLE PRECISION"/>
            <type name="java.lang.Double"/>
        </property>
        <property name="mouse10">
            <column name="MOUSE10" not-null="false" unique="true" sql-type="DOUBLE PRECISION"/>
            <type name="java.lang.Double"/>
        </property>
        <one-to-one name="mouseGroup" class="mwk.pptp.androdomain.MouseGroupImpl"  property-ref="mouseCrosstab" cascade="none" lazy="proxy" fetch="select"/>
    </class>
</hibernate-mapping>
